{
  "seminar": "n. 研讨班，讲习会;研讨小组;研讨会;培训会;",
  "senate": "n. 参议院（美国、法国、澳大利亚等国家的两个立法机构之一）;上院;某些国家的)大学理事会;大学评议会;",
  "sensation": "n. 感觉;直觉;知觉;轰动;",
  "sentiment": "n. 感情，情绪;情操;意见，观点;感伤;",
  "setback": "n. 挫折;阻碍;退步;逆流;",
  "severe": "adj. 严峻的;严厉的;剧烈的;苛刻的;",
  "shabby": "adj. 破旧的，衣衫褴褛的;卑鄙的;悭吝的;低劣的，下流的;",
  "shaft": "n. 柄，轴;矛，箭;〈非〉嘲笑;光线;",
  "sham": "n. 赝品;假冒;骗子;套;枕套;",
  "shatter": "vt. 使破碎，使碎裂，砸碎;使…成为泡影;使…痛不欲生;使…散开;",
  "shear": "vt. 剪羊毛;切断;剪切;剥夺;",
  "shed": "n. 棚，库;分水岭;",
  "sheer": "v. （使）偏航，（使）转向;",
  "shilling": "n. 先令（英国1971年以前的货币单位，为一镑的二十分之一）;",
  "shiver": "n. 发抖，颤抖;碎块，破片;",
  "quiver": "vt.& vi. 微颤，抖动;",
  "shopkeeper": "n. 店主，老板;",
  "shorthand": "n. 速记;速记法;简略的表达方式;",
  "shove": "vt.& vi. 推，猛推;",
  "shrewd": "adj. 精明的，敏锐的;奸诈的，狡猾的;有眼光的;精于盘算的;",
  "shrink": "vt.& vi. 收缩，皱缩;（使）缩水;退缩，畏缩;",
  "shutter": "n. 遮光器;百叶窗;快门;",
  "siege": "n. 围攻，围困，围城（期间）;不断袭击;长期努力;",
  "besiege": "vt. 包围，为敌对势力包围;拥挤在周围，包围住;如被询问纠缠或强求;使感到丧气或焦虑;",
  "sightseeing": "n. 观光，游览;",
  "signify": "vt. 表示…的意思;意味;预示;",
  "simultaneous": "adj. 同时发生的，同时存在的;同时的;联立的;",
  "sip": "n. 呷的动作;一呷之量;",
  "siren": "n. 汽笛，警报声"
}
